[
  {
    "Title": "13 lives (Prime) 2h27m",
    "STATUS": "",
    "WATCHED": "",
    "OwnerShip": "",
    "GENRE": "",
    "RUNTIME": "",
    "Link": "",
    "DESCRIPTION": ""
  },
  {
    "Title": "2001 Space Odyssey (HBO) 2h29m",
    "STATUS": "",
    "WATCHED": "",
    "OwnerShip": "",
    "GENRE": "",
    "RUNTIME": "",
    "Link": "",
    "DESCRIPTION": ""
  },
  {
    "Title": "65 (Netflix) 1h 32m 👀",
    "STATUS": "",
    "WATCHED": "👀",
    "OwnerShip": "",
    "GENRE": "",
    "RUNTIME": "",
    "Link": "",
    "DESCRIPTION": ""
  },
  {
    "Title": "A Time to Kill (Prime) 2h25m",
    "STATUS": "",
    "WATCHED": "",
    "OwnerShip": "",
    "GENRE": "",
    "RUNTIME": "",
    "Link": "",
    "DESCRIPTION": ""
  },
  {
    "Title": "Ant-Man (Disney+) 117 minutes",
    "STATUS": "",
    "WATCHED": "",
    "OwnerShip": "",
    "GENRE": "",
    "RUNTIME": "",
    "Link": "",
    "DESCRIPTION": ""
  },
  {
    "Title": "Ant-Man and the Wasp (Disney+) 118 minutes",
    "STATUS": "",
    "WATCHED": "",
    "OwnerShip": "",
    "GENRE": "",
    "RUNTIME": "",
    "Link": "",
    "DESCRIPTION": ""
  },
  {
    "Title": "Archive (PRIME) 1h49m ",
    "STATUS": "🟢",
    "WATCHED": "👀",
    "OwnerShip": "PRIME - free",
    "GENRE": "Sci-Fi",
    "RUNTIME": "",
    "Link": "",
    "DESCRIPTION": ""
  },
  {
    "Title": "Avengers: Age of Ultron (Disney+) 141 minutes",
    "STATUS": "🟢",
    "WATCHED": "👀",
    "OwnerShip": "DISNEY+",
    "GENRE": "Super Hero, Action",
    "RUNTIME": "",
    "Link": "",
    "DESCRIPTION": ""
  },
  {
    "Title": "Avengers: Endgame (Disney+) 181 minutes",
    "STATUS": "",
    "WATCHED": "",
    "OwnerShip": "",
    "GENRE": "",
    "RUNTIME": "",
    "Link": "",
    "DESCRIPTION": ""
  },
  {
    "Title": "Avengers: Infinity War (Disney+) 149 minutes",
    "STATUS": "",
    "WATCHED": "",
    "OwnerShip": "",
    "GENRE": "",
    "RUNTIME": "",
    "Link": "",
    "DESCRIPTION": ""
  },
  {
    "Title": "Black Adam (HBO) 2h5m 👀",
    "STATUS": "",
    "WATCHED": "👀",
    "OwnerShip": "",
    "GENRE": "",
    "RUNTIME": "",
    "Link": "",
    "DESCRIPTION": ""
  },
  {
    "Title": "Black Panther (Disney+) 134 minutes",
    "STATUS": "",
    "WATCHED": "",
    "OwnerShip": "",
    "GENRE": "",
    "RUNTIME": "",
    "Link": "",
    "DESCRIPTION": ""
  },
  {
    "Title": "Black Panther: Wakanda Forever (Disney+) 161 minutes",
    "STATUS": "",
    "WATCHED": "",
    "OwnerShip": "",
    "GENRE": "",
    "RUNTIME": "",
    "Link": "",
    "DESCRIPTION": ""
  },
  {
    "Title": "Black Widow (Disney+) 134 minutes",
    "STATUS": "",
    "WATCHED": "",
    "OwnerShip": "",
    "GENRE": "",
    "RUNTIME": "",
    "Link": "",
    "DESCRIPTION": ""
  },
  {
    "Title": "Black Widow (Disney+) 2h16m 👀",
    "STATUS": "",
    "WATCHED": "👀",
    "OwnerShip": "",
    "GENRE": "",
    "RUNTIME": "",
    "Link": "",
    "DESCRIPTION": ""
  },
  {
    "Title": "Bright (Netflix) Duration 1h58m - {fantasy}",
    "STATUS": "🟢",
    "WATCHED": "",
    "OwnerShip": "NETFLIX",
    "GENRE": "Fantasy",
    "RUNTIME": "",
    "Link": "",
    "DESCRIPTION": ""
  },
  {
    "Title": "Brightburn (Xbox) 1h 30m",
    "STATUS": "",
    "WATCHED": "",
    "OwnerShip": "",
    "GENRE": "",
    "RUNTIME": "",
    "Link": "",
    "DESCRIPTION": ""
  },
  {
    "Title": "Captain America: Civil War (Disney+) 147 minutes",
    "STATUS": "",
    "WATCHED": "",
    "OwnerShip": "",
    "GENRE": "",
    "RUNTIME": "",
    "Link": "",
    "DESCRIPTION": ""
  },
  {
    "Title": "Captain America: The First Avenger (Disney+) 124 minutes👀",
    "STATUS": "",
    "WATCHED": "👀",
    "OwnerShip": "",
    "GENRE": "",
    "RUNTIME": "",
    "Link": "",
    "DESCRIPTION": ""
  },
  {
    "Title": "Captain America: The Winter Soldier (Disney+) 136 minutes👀",
    "STATUS": "",
    "WATCHED": "👀",
    "OwnerShip": "",
    "GENRE": "",
    "RUNTIME": "",
    "Link": "",
    "DESCRIPTION": ""
  },
  {
    "Title": "Captain Marvel (Disney+) 123 minutes👀",
    "STATUS": "",
    "WATCHED": "👀",
    "OwnerShip": "",
    "GENRE": "",
    "RUNTIME": "",
    "Link": "",
    "DESCRIPTION": ""
  },
  {
    "Title": "Children of Men (Prime) 1h49m 👀",
    "STATUS": "",
    "WATCHED": "👀",
    "OwnerShip": "",
    "GENRE": "",
    "RUNTIME": "",
    "Link": "",
    "DESCRIPTION": ""
  },
  {
    "Title": "Close Encounters of the Third Kind (Prime) 2h17m",
    "STATUS": "",
    "WATCHED": "",
    "OwnerShip": "",
    "GENRE": "",
    "RUNTIME": "",
    "Link": "",
    "DESCRIPTION": ""
  },
  {
    "Title": "Constantine (HBO) 2h1m👀",
    "STATUS": "",
    "WATCHED": "👀",
    "OwnerShip": "",
    "GENRE": "",
    "RUNTIME": "",
    "Link": "",
    "DESCRIPTION": ""
  },
  {
    "Title": "Contact (HBO Max) 2h 30m👀",
    "STATUS": "",
    "WATCHED": "👀",
    "OwnerShip": "",
    "GENRE": "",
    "RUNTIME": "",
    "Link": "",
    "DESCRIPTION": ""
  },
  {
    "Title": "Dark City (HBO Max) 100 mins 👀",
    "STATUS": "",
    "WATCHED": "👀",
    "OwnerShip": "",
    "GENRE": "",
    "RUNTIME": "",
    "Link": "",
    "DESCRIPTION": ""
  },
  {
    "Title": "Doctor Strange (Disney+) 115 minutes👀",
    "STATUS": "",
    "WATCHED": "👀",
    "OwnerShip": "",
    "GENRE": "",
    "RUNTIME": "",
    "Link": "",
    "DESCRIPTION": ""
  },
  {
    "Title": "Doctor Strange: In the Multiverse of Madness (Disney+) 2h8m ",
    "STATUS": "",
    "WATCHED": "👀👀",
    "OwnerShip": "",
    "GENRE": "",
    "RUNTIME": "",
    "Link": "",
    "DESCRIPTION": ""
  },
  {
    "Title": "Doors (Prime) 1h 21m 👀",
    "STATUS": "",
    "WATCHED": "👀",
    "OwnerShip": "",
    "GENRE": "",
    "RUNTIME": "",
    "Link": "",
    "DESCRIPTION": ""
  },
  {
    "Title": "Dredd (Prime) 1h35m",
    "STATUS": "🟢",
    "WATCHED": "",
    "OwnerShip": "PRIME - buy or rent",
    "GENRE": "Super Hero, Crime",
    "RUNTIME": "",
    "Link": "",
    "DESCRIPTION": ""
  },
  {
    "Title": "Dungeons & Dragons: Honor Among Thieves (PRIME) 2h10m👀",
    "STATUS": "",
    "WATCHED": "👀",
    "OwnerShip": "",
    "GENRE": "",
    "RUNTIME": "",
    "Link": "",
    "DESCRIPTION": ""
  },
  {
    "Title": "Equilibrium",
    "STATUS": "",
    "WATCHED": "👀",
    "OwnerShip": "",
    "GENRE": "Action & Adventure, Science-Fiction, Mystery & Thriller, Drama, Tech Noir",
    "RUNTIME": "1h 47min",
    "Link": "https://www.justwatch.com/us/movie/equilibrium",
    "DESCRIPTION": "In a dystopian future, a totalitarian regime maintains peace by subduing the populace with a drug, and displays of emotion are punishable by death. A man in charge of enforcing the law rises to overthrow the system."
  },
  {
    "Title": "Eternals (2021)",
    "STATUS": "",
    "WATCHED": "👀",
    "OwnerShip": "",
    "GENRE": "",
    "RUNTIME": "2h 36min",
    "Link": "https://www.justwatch.com/us/movie/eternals",
    "DESCRIPTION": ""
  },
  {
    "Title": "Grosse pointe blank (Prime) 1h47m",
    "STATUS": "",
    "WATCHED": "",
    "OwnerShip": "",
    "GENRE": "",
    "RUNTIME": "",
    "Link": "",
    "DESCRIPTION": ""
  },
  {
    "Title": "Guardians of the Galaxy (Disney+) 121 minutes",
    "STATUS": "",
    "WATCHED": "",
    "OwnerShip": "",
    "GENRE": "",
    "RUNTIME": "",
    "Link": "",
    "DESCRIPTION": ""
  },
  {
    "Title": "Guardians of the Galaxy Vol. 2 (Disney+) 136 minutes👀",
    "STATUS": "",
    "WATCHED": "👀",
    "OwnerShip": "",
    "GENRE": "",
    "RUNTIME": "",
    "Link": "",
    "DESCRIPTION": ""
  },
  {
    "Title": "Heaven knows what (Prime) 1h37m",
    "STATUS": "",
    "WATCHED": "",
    "OwnerShip": "",
    "GENRE": "",
    "RUNTIME": "",
    "Link": "",
    "DESCRIPTION": ""
  },
  {
    "Title": "Iron Man (Disney+) 126 minutes👀",
    "STATUS": "",
    "WATCHED": "👀",
    "OwnerShip": "",
    "GENRE": "",
    "RUNTIME": "",
    "Link": "",
    "DESCRIPTION": ""
  },
  {
    "Title": "Iron Man 2 (Disney+) 124 minutes👀",
    "STATUS": "",
    "WATCHED": "👀",
    "OwnerShip": "",
    "GENRE": "",
    "RUNTIME": "",
    "Link": "",
    "DESCRIPTION": ""
  },
  {
    "Title": "Iron Man 3 (Disney+) 130 minutes👀",
    "STATUS": "",
    "WATCHED": "👀",
    "OwnerShip": "",
    "GENRE": "",
    "RUNTIME": "",
    "Link": "",
    "DESCRIPTION": ""
  },
  {
    "Title": "Judge Dredd (Prime) 1h36m",
    "STATUS": "",
    "WATCHED": "",
    "OwnerShip": "",
    "GENRE": "",
    "RUNTIME": "",
    "Link": "",
    "DESCRIPTION": ""
  },
  {
    "Title": "Lucy (Netflix) ",
    "STATUS": "",
    "WATCHED": "👀",
    "OwnerShip": "",
    "GENRE": "",
    "RUNTIME": "",
    "Link": "",
    "DESCRIPTION": ""
  },
  {
    "Title": "Marvel's The Avengers (Disney+) 143 minutes👀",
    "STATUS": "",
    "WATCHED": "👀",
    "OwnerShip": "",
    "GENRE": "",
    "RUNTIME": "",
    "Link": "",
    "DESCRIPTION": ""
  },
  {
    "Title": "Morbius (Disney+) 1h44m👀",
    "STATUS": "",
    "WATCHED": "👀",
    "OwnerShip": "",
    "GENRE": "",
    "RUNTIME": "",
    "Link": "",
    "DESCRIPTION": ""
  },
  {
    "Title": "Mulholland Drive (Criterion Channel",
    "STATUS": " Hulu) 121 mins",
    "WATCHED": "",
    "OwnerShip": "",
    "GENRE": "",
    "RUNTIME": "",
    "Link": "",
    "DESCRIPTION": ""
  },
  {
    "Title": "Nope",
    "STATUS": "",
    "WATCHED": "👀",
    "OwnerShip": "",
    "GENRE": "",
    "RUNTIME": "",
    "Link": "",
    "DESCRIPTION": ""
  },
  {
    "Title": "When We Were Kings (1996)",
    "STATUS": "",
    "WATCHED": "",
    "OwnerShip": "Subscription",
    "GENRE": "History, Music & Musical, Documentary, Sport",
    "RUNTIME": "1h 29min",
    "Link": "https://www.justwatch.com/us/movie/when-we-were-kings",
    "DESCRIPTION": "It's 1974. Muhammad Ali is 32 and thought by many to be past his prime. George Foreman is ten years younger and the heavyweight champion of the world. Promoter Don King wants to make a name for himself and offers both fighters five million dollars apiece to fight one another, and when they accept, King has only to come up with the money. He finds a willing backer in Mobutu Sese Suko, the dictator of Zaire, and the 'Rumble in the Jungle' is set, including a musical festival featuring some of America's top black performers, like James Brown and B.B. King."
  },
  {
    "Title": "Where to Invade Next (2015)",
    "STATUS": "🟢",
    "WATCHED": "",
    "OwnerShip": "Subscription",
    "GENRE": "Documentary, Comedy",
    "RUNTIME": "2h 1min",
    "Link": "https://www.justwatch.com/us/movie/where-to-invade-next",
    "DESCRIPTION": "To understand firsthand what the United States of America can learn from other nations, Michael Moore playfully “invades” some to see what they have to offer."
  },
  {
    "Title": "ReMastered: Who Shot the Sheriff(2018)",
    "STATUS": "",
    "WATCHED": "",
    "OwnerShip": "Subscription",
    "GENRE": "Documentary, Crime, History, Music & Musical",
    "RUNTIME": "57min",
    "Link": "https://www.justwatch.com/us/movie/remastered-who-shot-the-sheriff",
    "DESCRIPTION": "In 1976, reggae icon Bob Marley survived an assassination attempt as rival political groups battled in Jamaica. But who exactly was responsible?"
  },
  {
    "Title": "ZEF - The Story of Die Antwoord (2024)",
    "STATUS": "🟢",
    "WATCHED": "",
    "OwnerShip": "Subscription",
    "GENRE": "Documentary, Music & Musical, Music Biopics",
    "RUNTIME": "1h 30min",
    "Link": "https://www.justwatch.com/us/movie/zef-the-story-of-die-antwoord",
    "DESCRIPTION": "South African producer / director JON DAY spent the last 5 years making a documentary about the mysterious rap-rave group, DIE ANTWOORD. Art directed by surrealist photographer, ROGER BALLEN. Narrated by NINJA & ¥O-LANDI'S daughter, 16 JONES."
  }
]